[
  {
    "source_filename": "IMG_4712.jpg",
    "source_basename": "IMG_4712",
    "approved_filename": "sweet-fork-patriotic-vintage-buttercream-cake-centerville-utah.jpg",
    "category": "Custom Cakes",
    "title": "Patriotic Vintage Buttercream Cake",
    "alt_text": "White custom cake with red and blue vintage-style buttercream piping and blue bows on a wooden cake stand.",
    "tags": ["custom cake", "patriotic cake", "vintage cake", "buttercream cake", "red white and blue cake", "birthday cake"],
    "visibility": "published",
    "featured": false,
    "sort_priority": "medium",
    "suggested_use": "Customer-facing gallery",
    "recommended_crop": "4:5 portrait",
    "notes": "Strong finished-cake image. Niche patriotic theme, so good for gallery but probably not homepage-featured."
  },
  {
    "source_filename": "IMG_4714.jpg",
    "source_basename": "IMG_4714",
    "approved_filename": "sweet-fork-golf-cart-sweet-16-birthday-cake-centerville-utah.jpg",
    "category": "Custom Cakes",
    "title": "Golf Cart Sweet 16 Cake",
    "alt_text": "Custom golf-themed birthday cake with a golf cart topper, putting green design, and piped birthday lettering.",
    "tags": ["custom cake", "golf cake", "birthday cake", "sweet 16 cake", "teen birthday cake", "sports theme cake"],
    "visibility": "published",
    "featured": false,
    "sort_priority": "medium",
    "suggested_use": "Customer-facing gallery",
    "recommended_crop": "4:5 portrait",
    "notes": "Good themed birthday example. Avoid using customer name in title/alt."
  },
  {
    "source_filename": "IMG_4709.jpg",
    "source_basename": "IMG_4709",
    "approved_filename": "sweet-fork-golf-65th-birthday-cake-centerville-utah.jpg",
    "category": "Custom Cakes",
    "title": "Golf-Themed 65th Birthday Cake",
    "alt_text": "White custom birthday cake decorated as a golf course with piped grass, sand trap detail, flag, and golfer silhouette.",
    "tags": ["custom cake", "golf cake", "milestone birthday cake", "65th birthday cake", "sports theme cake", "celebration cake"],
    "visibility": "published",
    "featured": false,
    "sort_priority": "medium",
    "suggested_use": "Customer-facing gallery",
    "recommended_crop": "4:5 portrait",
    "notes": "Another strong golf-themed custom cake. Good supporting image in custom cakes."
  },
  {
    "source_filename": "IMG_4711.jpg",
    "source_basename": "IMG_4711",
    "approved_filename": "sweet-fork-holiday-macarons-assortment-tray-centerville-utah.jpg",
    "category": "Macarons",
    "title": "Holiday Macaron Assortment",
    "alt_text": "Assorted holiday macarons in festive Christmas colors and patterns arranged on a serving tray.",
    "tags": ["macarons", "holiday macarons", "christmas desserts", "french macarons", "dessert assortment", "festive treats"],
    "visibility": "published",
    "featured": false,
    "sort_priority": "medium",
    "suggested_use": "Customer-facing gallery",
    "recommended_crop": "original landscape",
    "notes": "Seasonal image. Great for macarons gallery, especially during holiday season."
  },
  {
    "source_filename": "IMG_4713.jpg",
    "source_basename": "IMG_4713",
    "approved_filename": "sweet-fork-floral-sixtieth-celebration-cake-centerville-utah.jpg",
    "category": "Custom Cakes",
    "title": "Floral Sixtieth Celebration Cake",
    "alt_text": "Two-tier white celebration cake with textured buttercream, fresh florals, and a glitter 'Sixty' topper.",
    "tags": ["custom cake", "floral cake", "celebration cake", "milestone birthday cake", "elegant cake", "two tier cake"],
    "visibility": "published",
    "featured": true,
    "sort_priority": "high",
    "suggested_use": "Customer-facing gallery",
    "recommended_crop": "4:5 portrait",
    "notes": "One of the strongest images in this set. Elegant, polished, and broadly appealing."
  },
  {
    "source_filename": "IMG_4716.jpg",
    "source_basename": "IMG_4716",
    "approved_filename": "sweet-fork-cake-tasting-box-assortment-centerville-utah.jpg",
    "category": "Wedding Cakes",
    "title": "Cake Tasting Box",
    "alt_text": "Branded cake tasting box with assorted cake flavors in individual dessert containers and sample packaging.",
    "tags": ["cake tasting box", "wedding cake tasting", "cake samples", "dessert box", "wedding cakes", "consultation tasting"],
    "visibility": "published",
    "featured": true,
    "sort_priority": "high",
    "suggested_use": "Customer-facing gallery",
    "recommended_crop": "original collage",
    "notes": "Best fit under Wedding Cakes because current site categories are limited. Good supporting image for tasting/consultation marketing."
  },
  {
    "source_filename": "IMG_4719.jpg",
    "source_basename": "IMG_4719",
    "approved_filename": "sweet-fork-university-of-utah-celebration-cake-centerville-utah.jpg",
    "category": "Custom Cakes",
    "title": "University of Utah Celebration Cake",
    "alt_text": "White custom cake with a bold red university-inspired design, red and white buttercream swirls, and festive sprinkles.",
    "tags": ["custom cake", "university of utah cake", "college cake", "red and white cake", "celebration cake", "school spirit cake"],
    "visibility": "published",
    "featured": false,
    "sort_priority": "medium",
    "suggested_use": "Customer-facing gallery",
    "recommended_crop": "4:5 portrait",
    "notes": "Strong themed cake example. Good for school spirit or graduation-related browsing."
  },
  {
    "source_filename": "IMG_4715.jpg",
    "source_basename": "IMG_4715",
    "approved_filename": "sweet-fork-holiday-macaron-gift-box-assortment-centerville-utah.jpg",
    "category": "Macarons",
    "title": "Holiday Macaron Gift Box Assortment",
    "alt_text": "Collage of boxed holiday macarons including snowman, peppermint, gingerbread, hot cocoa, and white chocolate styles.",
    "tags": ["macarons", "holiday macarons", "macaron gift box", "christmas macarons", "seasonal desserts", "boxed treats"],
    "visibility": "published",
    "featured": false,
    "sort_priority": "medium",
    "suggested_use": "Customer-facing gallery",
    "recommended_crop": "1:1 square",
    "notes": "Seasonal collage. Great for macarons gallery and holiday marketing."
  },
  {
    "source_filename": "IMG_4710.jpg",
    "source_basename": "IMG_4710",
    "approved_filename": "sweet-fork-strawberry-first-birthday-cake-centerville-utah.jpg",
    "category": "Custom Cakes",
    "title": "Strawberry First Birthday Cake",
    "alt_text": "Pink first birthday cake with piped ruffles, strawberry details, daisy accents, and 'one' lettering.",
    "tags": ["custom cake", "first birthday cake", "strawberry cake", "pink cake", "girl birthday cake", "themed birthday cake"],
    "visibility": "published",
    "featured": true,
    "sort_priority": "high",
    "suggested_use": "Customer-facing gallery",
    "recommended_crop": "4:5 portrait",
    "notes": "Very strong customer-facing image. Good candidate for featured placement within Custom Cakes."
  },
  {
    "source_filename": "IMG_4718.jpg",
    "source_basename": "IMG_4718",
    "approved_filename": "sweet-fork-elegant-raspberry-buttercream-cake-centerville-utah.jpg",
    "category": "Custom Cakes",
    "title": "Elegant Raspberry Buttercream Cake",
    "alt_text": "White buttercream cake topped with fresh raspberries and detailed vintage-style piping on a cake stand.",
    "tags": ["custom cake", "raspberry cake", "buttercream cake", "elegant cake", "vintage cake", "celebration cake"],
    "visibility": "published",
    "featured": true,
    "sort_priority": "high",
    "suggested_use": "Customer-facing gallery",
    "recommended_crop": "4:5 portrait",
    "notes": "Excellent broad-appeal image. Could also work well in wedding-related marketing if multi-assignment is supported."
  },
  {
    "source_filename": "IMG_4699.jpg",
    "source_basename": "IMG_4699",
    "approved_filename": "sweet-fork-strawberry-cookie-macaron-box-centerville-utah.jpg",
    "category": "Sugar Cookies",
    "title": "Strawberry Cookie and Macaron Box",
    "alt_text": "Gift box with strawberry-themed decorated sugar cookies, flower cookies, and pink and red macarons.",
    "tags": ["sugar cookies", "decorated cookies", "strawberry cookies", "macarons", "cookie box", "party treats"],
    "visibility": "published",
    "featured": true,
    "sort_priority": "high",
    "suggested_use": "Customer-facing gallery",
    "recommended_crop": "4:5 portrait or square",
    "notes": "Strong image with good color and product variety. Good candidate for sugar cookies gallery and seasonal/social use."
  },
  {
    "source_filename": "IMG_4704.jpg",
    "source_basename": "IMG_4704",
    "approved_filename": "sweet-fork-st-patricks-day-diy-cookie-kit-centerville-utah.jpg",
    "category": "Sugar Cookies",
    "title": "St. Patrick's Day DIY Cookie Kit",
    "alt_text": "St. Patrick's Day DIY cookie decorating kit with shamrock cookies, frosting bags, sprinkles, and decorating instructions.",
    "tags": ["sugar cookies", "DIY cookie kit", "St. Patrick's Day cookies", "cookie decorating kit", "seasonal cookies", "holiday treats"],
    "visibility": "published",
    "featured": false,
    "sort_priority": "medium",
    "suggested_use": "Customer-facing gallery / seasonal gallery",
    "recommended_crop": "square",
    "notes": "Useful seasonal product image. Since DIY kits may be less emphasized on v2, keep as supporting gallery content rather than a featured item."
  },
  {
    "source_filename": "IMG_4701.jpg",
    "source_basename": "IMG_4701",
    "approved_filename": "sweet-fork-christmas-holiday-macarons-centerville-utah.jpg",
    "category": "Macarons",
    "title": "Christmas Holiday Macarons",
    "alt_text": "Holiday macarons in festive Christmas colors arranged on a cake stand with Christmas decor.",
    "tags": ["macarons", "holiday macarons", "Christmas macarons", "seasonal desserts", "festive treats", "dessert display"],
    "visibility": "published",
    "featured": false,
    "sort_priority": "medium",
    "suggested_use": "Macarons gallery / seasonal marketing",
    "recommended_crop": "4:5 portrait",
    "notes": "Great seasonal lifestyle image. Best used during the holiday season or in the macarons section."
  },
  {
    "source_filename": "IMG_4706.jpg",
    "source_basename": "IMG_4706",
    "approved_filename": "sweet-fork-assorted-seasonal-macarons-centerville-utah.jpg",
    "category": "Macarons",
    "title": "Assorted Seasonal Macarons",
    "alt_text": "Assorted seasonal macarons with pie, cocoa, cream, and fall-inspired designs arranged on a marble tray.",
    "tags": ["macarons", "seasonal macarons", "assorted macarons", "fall desserts", "custom macarons", "dessert assortment"],
    "visibility": "published",
    "featured": false,
    "sort_priority": "medium",
    "suggested_use": "Macarons gallery",
    "recommended_crop": "landscape or square",
    "notes": "Solid macaron variety image. Useful for showing flavor/design range."
  },
  {
    "source_filename": "IMG_4703.jpg",
    "source_basename": "IMG_4703",
    "approved_filename": "sweet-fork-merry-bright-christmas-cookie-kit-centerville-utah.jpg",
    "category": "Sugar Cookies",
    "title": "Merry & Bright Christmas Cookie Kit",
    "alt_text": "Merry and Bright Christmas cookie decorating kit with shaped sugar cookies, frosting, sprinkles, and edible glitter dust.",
    "tags": ["sugar cookies", "Christmas cookie kit", "DIY cookie kit", "holiday cookies", "cookie decorating kit", "seasonal treats"],
    "visibility": "published",
    "featured": false,
    "sort_priority": "medium",
    "suggested_use": "Seasonal gallery / holiday marketing",
    "recommended_crop": "square",
    "notes": "Good branded product packaging image. Use seasonally; not a top evergreen homepage image."
  },
  {
    "source_filename": "IMG_4708.jpg",
    "source_basename": "IMG_4708",
    "approved_filename": "sweet-fork-st-patricks-day-rainbow-cupcakes-centerville-utah.jpg",
    "category": "Cupcakes",
    "title": "St. Patrick's Day Rainbow Cupcakes",
    "alt_text": "St. Patrick's Day cupcakes with green frosting, rainbow buttercream, gold accents, and festive decorations.",
    "tags": ["cupcakes", "St. Patrick's Day cupcakes", "rainbow cupcakes", "holiday cupcakes", "custom cupcakes", "seasonal desserts"],
    "visibility": "published",
    "featured": false,
    "sort_priority": "medium",
    "suggested_use": "Cupcakes gallery / seasonal gallery",
    "recommended_crop": "landscape or square",
    "notes": "Strong seasonal cupcake image. Good for cupcake variety, especially around March."
  },
  {
    "source_filename": "IMG_4700.jpg",
    "source_basename": "IMG_4700",
    "approved_filename": "sweet-fork-jurassic-world-dinosaur-sugar-cookies-centerville-utah.jpg",
    "category": "Sugar Cookies",
    "title": "Dinosaur-Themed Sugar Cookies",
    "alt_text": "Dinosaur-themed decorated sugar cookies with Jurassic-style details, dinosaur eyes, bones, and number eight cookies.",
    "tags": ["sugar cookies", "decorated cookies", "dinosaur cookies", "birthday cookies", "themed cookies", "kids birthday treats"],
    "visibility": "published",
    "featured": true,
    "sort_priority": "high",
    "suggested_use": "Customer-facing gallery",
    "recommended_crop": "square",
    "notes": "Very strong themed sugar cookie example. I avoided using the protected movie title in the public title, but kept the filename descriptive enough."
  },
  {
    "source_filename": "IMG_4705.jpg",
    "source_basename": "IMG_4705",
    "approved_filename": "sweet-fork-floral-number-birthday-cake-centerville-utah.jpg",
    "category": "Custom Cakes",
    "title": "Floral Number Birthday Cake",
    "alt_text": "Number-shaped birthday cake decorated with piped flowers, sunflowers, daisies, ladybugs, and a gold birthday topper.",
    "tags": ["custom cake", "number cake", "birthday cake", "floral cake", "sunflower cake", "celebration cake"],
    "visibility": "published",
    "featured": true,
    "sort_priority": "high",
    "suggested_use": "Customer-facing gallery",
    "recommended_crop": "landscape or square",
    "notes": "Strong custom cake image. Broadly useful because it shows detailed piping and shaped cake capability."
  },
  {
    "source_filename": "IMG_4702.jpg",
    "source_basename": "IMG_4702",
    "approved_filename": "sweet-fork-valentine-heart-sugar-cookie-box-centerville-utah.jpg",
    "category": "Sugar Cookies",
    "title": "Valentine Heart Sugar Cookie Box",
    "alt_text": "Box of decorated heart-shaped Valentine sugar cookies in red, pink, and white designs.",
    "tags": ["sugar cookies", "Valentine cookies", "heart cookies", "decorated cookies", "cookie box", "seasonal treats"],
    "visibility": "published",
    "featured": false,
    "sort_priority": "medium",
    "suggested_use": "Sugar Cookies gallery / seasonal gallery",
    "recommended_crop": "landscape or square",
    "notes": "Good seasonal cookie box image. Strong around Valentine's Day, but secondary priority for evergreen gallery."
  },
  {
    "source_filename": "IMG_4707.jpg",
    "source_basename": "IMG_4707",
    "approved_filename": "sweet-fork-blue-macaron-number-cake-centerville-utah.jpg",
    "category": "Custom Cakes",
    "title": "Blue Macaron Number Cake",
    "alt_text": "Blue and white number cake decorated with macarons, buttercream piping, and silver disco ball accents.",
    "tags": ["custom cake", "number cake", "macaron cake", "birthday cake", "blue cake", "celebration cake"],
    "visibility": "published",
    "featured": true,
    "sort_priority": "high",
    "suggested_use": "Customer-facing gallery",
    "recommended_crop": "landscape or square",
    "notes": "Strong specialty cake image and good cross-over example between custom cakes and macarons."
  }
]
